{
  "generated_at": "2026-06-15T19:55:27.528348+00:00",
  "window_start": "2026-06-14",
  "window_end": "2026-06-21",
  "source": "Pickx via iptv-org/epg",
  "watchlist_size": 21,
  "watchlist": [
    "Kathryn Bigelow",
    "Howard Hawks",
    "Ernst Lubitsch",
    "Frank Capra",
    "Preston Sturges",
    "Nicole Garcia",
    "Philippe de Broca",
    "Mario Monicelli",
    "David Fincher",
    "Olivia Newman",
    "Denis Villeneuve",
    "Christopher Nolan",
    "Billy Wilder",
    "John Hughes",
    "Ridley Scott",
    "Alfred Hitchcock",
    "Sydney Pollack",
    "Blake Edwards",
    "Guy Ritchie",
    "Harold Ramis",
    "Fernando Trueba"
  ],
  "count": 5,
  "programmes": [
    {
      "start": "2026-06-14T11:25:00+00:00",
      "stop": "2026-06-14T13:00:00+00:00",
      "channel": "BBC Two",
      "title": "Strangers on a Train",
      "subtitle": "",
      "directors": [
        "Alfred Hitchcock"
      ],
      "matched_director": "Alfred Hitchcock",
      "actors": [
        "Farley Granger",
        "Robert Walker",
        "Ruth Roman",
        "Leo G. Carroll",
        "Patricia Hitchcock",
        "Marion Lorne"
      ],
      "description": "A deranged socialite accosts a tennis star with his theory that if two strangers trade murders, they can disguise their motives and avoid suspicion.",
      "category": "Movies"
    },
    {
      "start": "2026-06-14T13:00:00+00:00",
      "stop": "2026-06-14T14:45:00+00:00",
      "channel": "BBC Two",
      "title": "Dial M for Murder",
      "subtitle": "",
      "directors": [
        "Alfred Hitchcock"
      ],
      "matched_director": "Alfred Hitchcock",
      "actors": [
        "Ray Milland",
        "Grace Kelly",
        "Robert Cummings",
        "John Williams",
        "Anthony Dawson",
        "Leo Britt"
      ],
      "description": "An ex-tennis pro carries out a plot to have his wife murdered after discovering she is having an affair, and assumes she will soon leave him for the other man anyway. When things go wrong, he improvises a new plan—to frame her for murder instead. Now Wendice must frantically scheme to outwit the police and avoid having his plot detected.",
      "category": "Movies"
    },
    {
      "start": "2026-06-15T14:47:00+00:00",
      "stop": "2026-06-15T17:11:00+00:00",
      "channel": "Action",
      "title": "Chouans !",
      "subtitle": "",
      "directors": [
        "Philippe de Broca"
      ],
      "matched_director": "Philippe de Broca",
      "actors": [
        "Philippe Noiret",
        "Vincent Schmitt",
        "Raoul Billerey",
        "Claudine Delvaux",
        "Jean Parédès",
        "Sophie Marceau"
      ],
      "description": "L'histoire d'une famille noble et éclairée, celle du comte Savinien de Kerfadec, lors des grandes révoltes chouannes dans les campagnes vendeenne et bretonne. L'histoire de ses enfants, dechirés entre le souffle de l'esprit révolutionnaire et la resistance épique des blancs a la montée de l'opportuniste bourgeoisie.",
      "category": "Cinéma"
    },
    {
      "start": "2026-06-16T06:01:00+00:00",
      "stop": "2026-06-16T08:25:00+00:00",
      "channel": "Action",
      "title": "Chouans !",
      "subtitle": "",
      "directors": [
        "Philippe de Broca"
      ],
      "matched_director": "Philippe de Broca",
      "actors": [
        "Philippe Noiret",
        "Vincent Schmitt",
        "Raoul Billerey",
        "Claudine Delvaux",
        "Jean Parédès",
        "Sophie Marceau"
      ],
      "description": "L'histoire d'une famille noble et éclairée, celle du comte Savinien de Kerfadec, lors des grandes révoltes chouannes dans les campagnes vendeenne et bretonne. L'histoire de ses enfants, dechirés entre le souffle de l'esprit révolutionnaire et la resistance épique des blancs a la montée de l'opportuniste bourgeoisie.",
      "category": "Cinéma"
    },
    {
      "start": "2026-06-21T23:45:00+00:00",
      "stop": "2026-06-22T01:25:00+00:00",
      "channel": "Arte",
      "title": "They Shot the Piano player",
      "subtitle": "",
      "directors": [
        "Fernando Trueba",
        "Javier Mariscal"
      ],
      "matched_director": "Fernando Trueba",
      "actors": [],
      "description": "New York, 2010. Jeff Harris, journaliste musical, cherche à découvrir la vérité sur Francisco Tenório Júnior, un jeune pianiste brésilien de samba-jazz disparu à Buenos Aires le 18 mars 1976. Tout en célébrant le mouvement musical latino Bossa Nova, le film capture une période éphémère regorgeant de liberté créatrice à un tournant de l'histoire de l'Amérique Latine dans les années 60 et 70, juste avant que le continent ne soit englouti par des régimes totalitaires.",
      "category": "Cinéma"
    }
  ]
}